pyPhenology/__init__.py
pyPhenology/utils.py
pyPhenology/data/aspen_obs.csv
pyPhenology/data/aspen_temperature.csv.gz
pyPhenology/data/vaccinium_obs.csv
pyPhenology/data/vaccinium_temperature.csv
pyPhenology/models/__init__.py
pyPhenology/models/alternating.py
pyPhenology/models/base.py
pyPhenology/models/chuine_models.py
pyPhenology/models/ensemble_models.py
pyPhenology/models/example_model.py
pyPhenology/models/sequential.py
pyPhenology/models/stat_models.py
pyPhenology/models/thermaltime.py
pyPhenology/models/validation.py
pyPhenology/models/weighted_model.py
pyPhenology/models/utils/__init__.py
pyPhenology/models/utils/misc.py
pyPhenology/models/utils/optimize.py
pyPhenology/models/utils/transforms.py
pyPhenology-0.7.1.dist-info/METADATA
pyPhenology-0.7.1.dist-info/RECORD
pyPhenology-0.7.1.dist-info/WHEEL
pyPhenology-0.7.1.dist-info/top_level.txt
