Metadata-Version: 2.1
Name: pyPhenology
Version: 0.7.1
Summary: Plant phenology models in python
Home-page: https://github.com/sdtaylor/pyPhenology
Author: Shawn Taylor
License: MIT
Platform: UNKNOWN
